portableDB/Examples.py
portableDB/__init__.py
portableDB/main.py
portableDB-2.2.dist-info/METADATA
portableDB-2.2.dist-info/WHEEL
portableDB-2.2.dist-info/top_level.txt
portableDB-2.2.dist-info/RECORD
