Metadata-Version: 2.2
Name: portableDB
Version: 2.2
Summary: This library is an easyest way to use local database!
Author: DoubleSquad
Requires-Dist: colorama>=0.4.6
Dynamic: author
Dynamic: description
Dynamic: description-content-type
Dynamic: requires-dist
Dynamic: summary
